cortex/__init__.py
cortex/auth.py
cortex/camel.py
cortex/client.py
cortex/connection.py
cortex/constant.py
cortex/content.py
cortex/env.py
cortex/exceptions.py
cortex/experiment/__init__.py
cortex/experiment/local.py
cortex/experiment/model.py
cortex/experiment/remote.py
cortex/message.py
cortex/models.py
cortex/properties.py
cortex/secrets.py
cortex/serviceconnector.py
cortex/session.py
cortex/skill.py
cortex/timer.py
cortex/types.py
cortex/utils.py
cortex/viz.py
cortex_python-7.0.0.dist-info/LICENSE
cortex_python-7.0.0.dist-info/METADATA
cortex_python-7.0.0.dist-info/WHEEL
cortex_python-7.0.0.dist-info/RECORD
