Metadata-Version: 2.1
Name: cortex-python
Version: 7.0.0
Summary: Python module for the Tecnotree Sensa Platform
License: Apache-2.0
Author: Tecnotree
Author-email: support@tecnotree.com
Requires-Python: >=3.9,<3.11
Classifier: License :: OSI Approved :: Apache Software License
Classifier: Programming Language :: Python :: 3
Classifier: Programming Language :: Python :: 3.9
Classifier: Programming Language :: Python :: 3.10
Provides-Extra: certifai
Provides-Extra: models-dev
Provides-Extra: models-runtime
Requires-Dist: certifai-evaluator-plugin ; extra == "certifai"
Requires-Dist: cortex-certifai-common ; extra == "certifai"
Requires-Dist: cortex_certifai_engine ; extra == "certifai"
Requires-Dist: cortex_certifai_model_sdk ; extra == "certifai"
Requires-Dist: cortex_certifai_scanner ; extra == "certifai"
Requires-Dist: cuid (>=0.3,<0.4)
Requires-Dist: dill (<=0.3.4)
Requires-Dist: ipython (>=8.10,<9) ; extra == "models-dev"
Requires-Dist: jinja2 (<4) ; extra == "models-dev"
Requires-Dist: matplotlib (>3,<4) ; extra == "models-dev"
Requires-Dist: mlflow (>2,<3) ; extra == "models-dev" or extra == "models-runtime"
Requires-Dist: pandas (<3) ; extra == "models-dev"
Requires-Dist: pyjwt[crypto] (<3)
Requires-Dist: python-dateutil (>=2.8.2,<3)
Requires-Dist: pytimeparse2 (>=1.7.1,<2.0.0)
Requires-Dist: pyyaml (>=5.4.1)
Requires-Dist: requests (>=2.31.0,<3)
Requires-Dist: requests-toolbelt (>=1.0.0)
Requires-Dist: seaborn (>0.13,<0.14) ; extra == "models-dev"
Requires-Dist: setuptools
